{
    "name": "Zeus",
    "attack_type": "Ranged",
    "roles": [
        "Nuker"
    ],
    "overall_winrate": "53.60%",
    "lanes": [
        {
            "lane": "Mid Lane",
            "presence": "65.22%",
            "win_rate": "56.53%"
        },
        {
            "lane": "Off Lane",
            "presence": "21.80%",
            "win_rate": "54.71%"
        },
        {
            "lane": "Safe Lane",
            "presence": "10.62%",
            "win_rate": "52.91%"
        }
    ],
    "primary_attribute": "intelligence",
    "win_rates": {
        "Broodmother": "47.43%",
        "Anti-Mage": "46.19%",
        "Visage": "46.34%",
        "Templar Assassin": "51.83%",
        "Lifestealer": "51.48%",
        "Lone Druid": "45.64%",
        "Chen": "52.06%",
        "Io": "56.81%",
        "Huskar": "51.65%",
        "Storm Spirit": "53.83%",
        "Lycan": "49.53%",
        "Spectre": "47.46%",
        "Enchantress": "57.45%",
        "Oracle": "55.67%",
        "Brewmaster": "52.85%",
        "Alchemist": "48.52%",
        "Ember Spirit": "55.60%",
        "Batrider": "56.22%",
        "Meepo": "50.02%",
        "Juggernaut": "51.97%",
        "Dazzle": "51.34%",
        "Centaur Warrunner": "52.55%",
        "Wraith King": "46.39%",
        "Warlock": "49.82%",
        "Tusk": "54.02%",
        "Chaos Knight": "52.37%",
        "Viper": "55.16%",
        "Undying": "51.41%",
        "Pudge": "52.06%",
        "Abaddon": "51.11%",
        "Bristleback": "52.47%",
        "Phantom Assassin": "52.46%",
        "Mars": "54.22%",
        "Faceless Void": "52.39%",
        "Kunkka": "55.28%",
        "Doom": "56.31%",
        "Omniknight": "54.48%",
        "Invoker": "54.77%",
        "Ogre Magi": "48.48%",
        "Ursa": "49.36%",
        "Tiny": "59.40%",
        "Skywrath Mage": "52.54%",
        "Death Prophet": "55.73%",
        "Snapfire": "53.97%",
        "Sven": "54.17%",
        "Clockwerk": "49.58%",
        "Timbersaw": "56.41%",
        "Void Spirit": "53.28%",
        "Bane": "50.77%",
        "Beastmaster": "48.86%",
        "Phoenix": "51.67%",
        "Dragon Knight": "51.04%",
        "Grimstroke": "56.53%",
        "Magnus": "57.90%",
        "Earth Spirit": "56.39%",
        "Shadow Shaman": "54.04%",
        "Legion Commander": "53.25%",
        "Lion": "54.94%",
        "Slardar": "52.30%",
        "Silencer": "53.54%",
        "Pangolier": "55.13%",
        "Keeper of the Light": "52.92%",
        "Arc Warden": "55.26%",
        "Clinkz": "51.73%",
        "Nature's Prophet": "58.14%",
        "Troll Warlord": "51.85%",
        "Treant Protector": "52.25%",
        "Shadow Demon": "56.16%",
        "Night Stalker": "50.25%",
        "Disruptor": "53.11%",
        "Crystal Maiden": "50.88%",
        "Techies": "53.40%",
        "Leshrac": "61.53%",
        "Vengeful Spirit": "51.25%",
        "Tidehunter": "52.69%",
        "Underlord": "49.59%",
        "Medusa": "53.15%",
        "Necrophos": "50.05%",
        "Bounty Hunter": "51.11%",
        "Spirit Breaker": "53.91%",
        "Rubick": "57.25%",
        "Dark Seer": "50.81%",
        "Witch Doctor": "53.44%",
        "Pugna": "54.53%",
        "Nyx Assassin": "53.48%",
        "Slark": "54.34%",
        "Lich": "52.74%",
        "Lina": "57.57%",
        "Venomancer": "52.63%",
        "Jakiro": "50.66%",
        "Winter Wyvern": "55.43%",
        "Dark Willow": "53.35%",
        "Gyrocopter": "58.67%",
        "Puck": "56.99%",
        "Ancient Apparition": "52.79%",
        "Mirana": "51.88%",
        "Elder Titan": "54.02%",
        "Razor": "53.91%",
        "Queen of Pain": "53.64%",
        "Windranger": "53.50%",
        "Axe": "53.06%",
        "Earthshaker": "55.51%",
        "Morphling": "57.07%",
        "Weaver": "55.14%",
        "Enigma": "54.26%",
        "Sniper": "52.68%",
        "Riki": "51.85%",
        "Monkey King": "56.69%",
        "Tinker": "60.22%",
        "Luna": "52.55%",
        "Phantom Lancer": "56.90%",
        "Bloodseeker": "52.12%",
        "Outworld Devourer": "60.86%",
        "Shadow Fiend": "56.45%",
        "Drow Ranger": "55.62%",
        "Naga Siren": "55.63%",
        "Sand King": "55.87%",
        "Terrorblade": "59.60%"
    }
}