{
    "name": "Abaddon",
    "attack_type": "Melee",
    "roles": [
        "Carry",
        "Durable",
        "Support"
    ],
    "overall_winrate": "50.83%",
    "lanes": [
        {
            "lane": "Off Lane",
            "presence": "61.67%",
            "win_rate": "56.09%"
        },
        {
            "lane": "Safe Lane",
            "presence": "31.00%",
            "win_rate": "53.53%"
        }
    ],
    "primary_attribute": "strength",
    "win_rates": {
        "Dark Seer": "44.75%",
        "Slark": "48.44%",
        "Outworld Devourer": "52.85%",
        "Meepo": "47.08%",
        "Broodmother": "49.20%",
        "Anti-Mage": "46.91%",
        "Pangolier": "50.89%",
        "Undying": "48.57%",
        "Ancient Apparition": "48.24%",
        "Monkey King": "50.91%",
        "Tiny": "55.45%",
        "Io": "55.58%",
        "Shadow Demon": "52.11%",
        "Keeper of the Light": "49.42%",
        "Nyx Assassin": "49.34%",
        "Lina": "53.07%",
        "Lion": "51.47%",
        "Earthshaker": "50.73%",
        "Razor": "49.50%",
        "Nature's Prophet": "54.27%",
        "Underlord": "46.38%",
        "Shadow Fiend": "50.83%",
        "Alchemist": "47.39%",
        "Faceless Void": "50.07%",
        "Beastmaster": "46.40%",
        "Grimstroke": "53.40%",
        "Invoker": "52.03%",
        "Elder Titan": "49.94%",
        "Lone Druid": "46.30%",
        "Rubick": "53.39%",
        "Windranger": "49.42%",
        "Enchantress": "55.62%",
        "Phantom Lancer": "51.57%",
        "Oracle": "54.22%",
        "Necrophos": "47.08%",
        "Bloodseeker": "47.27%",
        "Brewmaster": "51.70%",
        "Drow Ranger": "50.31%",
        "Sand King": "50.02%",
        "Naga Siren": "50.01%",
        "Lich": "49.49%",
        "Bristleback": "50.59%",
        "Weaver": "50.92%",
        "Sniper": "48.53%",
        "Lycan": "49.41%",
        "Tusk": "52.47%",
        "Snapfire": "51.74%",
        "Terrorblade": "53.44%",
        "Crystal Maiden": "48.43%",
        "Morphling": "53.04%",
        "Visage": "47.95%",
        "Vengeful Spirit": "48.76%",
        "Night Stalker": "47.98%",
        "Timbersaw": "54.03%",
        "Treant Protector": "49.86%",
        "Medusa": "50.47%",
        "Kunkka": "53.26%",
        "Omniknight": "52.56%",
        "Chen": "52.77%",
        "Dark Willow": "50.33%",
        "Tinker": "55.28%",
        "Leshrac": "58.24%",
        "Huskar": "52.06%",
        "Centaur Warrunner": "51.55%",
        "Viper": "53.61%",
        "Mars": "52.64%",
        "Pugna": "51.65%",
        "Wraith King": "45.94%",
        "Earth Spirit": "54.17%",
        "Tidehunter": "50.34%",
        "Phantom Assassin": "51.15%",
        "Doom": "54.41%",
        "Winter Wyvern": "52.48%",
        "Witch Doctor": "50.98%",
        "Void Spirit": "51.69%",
        "Riki": "48.42%",
        "Lifestealer": "52.79%",
        "Dragon Knight": "49.67%",
        "Magnus": "55.89%",
        "Clockwerk": "48.48%",
        "Techies": "51.36%",
        "Puck": "54.11%",
        "Sven": "52.78%",
        "Jakiro": "48.67%",
        "Bane": "49.75%",
        "Spirit Breaker": "51.85%",
        "Ursa": "48.67%",
        "Troll Warlord": "50.40%",
        "Disruptor": "51.49%",
        "Death Prophet": "54.44%",
        "Chaos Knight": "52.06%",
        "Ember Spirit": "55.35%",
        "Slardar": "51.09%",
        "Mirana": "49.80%",
        "Luna": "49.35%",
        "Templar Assassin": "53.87%",
        "Storm Spirit": "54.73%",
        "Legion Commander": "52.04%",
        "Ogre Magi": "48.10%",
        "Zeus": "48.89%",
        "Juggernaut": "52.01%",
        "Dazzle": "51.51%",
        "Enigma": "51.60%",
        "Spectre": "48.88%",
        "Pudge": "52.02%",
        "Queen of Pain": "51.85%",
        "Arc Warden": "54.33%",
        "Shadow Shaman": "53.35%",
        "Phoenix": "51.41%",
        "Gyrocopter": "56.79%",
        "Bounty Hunter": "50.32%",
        "Axe": "51.54%",
        "Warlock": "50.93%",
        "Skywrath Mage": "52.85%",
        "Venomancer": "52.08%",
        "Clinkz": "52.29%",
        "Batrider": "58.45%",
        "Silencer": "54.48%"
    }
}