{
    "name": "Chen",
    "attack_type": "Ranged",
    "roles": [
        "Jungler",
        "Pusher",
        "Support"
    ],
    "overall_winrate": "47.31%",
    "lanes": [
        {
            "lane": "Jungle",
            "presence": "50.38%",
            "win_rate": "46.33%"
        },
        {
            "lane": "Safe Lane",
            "presence": "21.49%",
            "win_rate": "48.03%"
        },
        {
            "lane": "Off Lane",
            "presence": "16.32%",
            "win_rate": "50.99%"
        },
        {
            "lane": "Roaming",
            "presence": "8.13%",
            "win_rate": "42.45%"
        }
    ],
    "primary_attribute": "intelligence",
    "win_rates": {
        "Troll Warlord": "43.77%",
        "Meepo": "43.71%",
        "Naga Siren": "44.91%",
        "Enigma": "44.92%",
        "Batrider": "49.52%",
        "Undying": "44.77%",
        "Omniknight": "47.03%",
        "Winter Wyvern": "47.18%",
        "Phantom Lancer": "47.26%",
        "Earthshaker": "47.22%",
        "Kunkka": "48.54%",
        "Sven": "47.42%",
        "Doom": "49.54%",
        "Slardar": "45.78%",
        "Weaver": "46.97%",
        "Slark": "47.11%",
        "Tidehunter": "45.90%",
        "Tiny": "52.54%",
        "Monkey King": "48.19%",
        "Bristleback": "46.96%",
        "Treant Protector": "45.88%",
        "Razor": "46.57%",
        "Medusa": "46.52%",
        "Earth Spirit": "49.97%",
        "Phantom Assassin": "47.13%",
        "Outworld Devourer": "51.65%",
        "Enchantress": "52.32%",
        "Dragon Knight": "45.42%",
        "Sniper": "45.21%",
        "Chaos Knight": "47.35%",
        "Nyx Assassin": "46.79%",
        "Tusk": "48.91%",
        "Crystal Maiden": "44.98%",
        "Brewmaster": "48.43%",
        "Axe": "46.08%",
        "Dark Seer": "44.68%",
        "Viper": "49.82%",
        "Lina": "50.50%",
        "Queen of Pain": "46.75%",
        "Morphling": "49.67%",
        "Death Prophet": "50.01%",
        "Lycan": "46.29%",
        "Spirit Breaker": "47.73%",
        "Jakiro": "44.72%",
        "Ancient Apparition": "46.40%",
        "Windranger": "46.83%",
        "Shadow Fiend": "48.41%",
        "Templar Assassin": "49.53%",
        "Sand King": "47.23%",
        "Timbersaw": "50.80%",
        "Bounty Hunter": "45.49%",
        "Faceless Void": "47.67%",
        "Dazzle": "47.32%",
        "Alchemist": "45.27%",
        "Venomancer": "46.73%",
        "Necrophos": "44.83%",
        "Ursa": "45.07%",
        "Visage": "45.33%",
        "Drow Ranger": "47.99%",
        "Lifestealer": "49.44%",
        "Skywrath Mage": "47.90%",
        "Invoker": "49.94%",
        "Abaddon": "47.24%",
        "Pangolier": "49.95%",
        "Lion": "49.83%",
        "Underlord": "44.80%",
        "Leshrac": "55.34%",
        "Snapfire": "49.33%",
        "Grimstroke": "51.46%",
        "Magnus": "52.65%",
        "Bane": "46.58%",
        "Disruptor": "48.22%",
        "Witch Doctor": "48.23%",
        "Legion Commander": "48.70%",
        "Pugna": "49.21%",
        "Huskar": "49.69%",
        "Broodmother": "49.12%",
        "Storm Spirit": "51.44%",
        "Vengeful Spirit": "46.78%",
        "Shadow Shaman": "49.61%",
        "Puck": "51.30%",
        "Void Spirit": "49.14%",
        "Riki": "45.97%",
        "Night Stalker": "46.15%",
        "Terrorblade": "51.53%",
        "Io": "54.80%",
        "Keeper of the Light": "48.65%",
        "Lich": "47.96%",
        "Mirana": "46.98%",
        "Clinkz": "47.66%",
        "Pudge": "48.72%",
        "Techies": "48.94%",
        "Ogre Magi": "45.27%",
        "Rubick": "52.24%",
        "Warlock": "47.29%",
        "Dark Willow": "48.57%",
        "Nature's Prophet": "53.43%",
        "Gyrocopter": "53.30%",
        "Luna": "46.89%",
        "Centaur Warrunner": "49.94%",
        "Silencer": "49.70%",
        "Mars": "51.14%",
        "Ember Spirit": "53.00%",
        "Phoenix": "48.50%",
        "Wraith King": "44.67%",
        "Anti-Mage": "47.61%",
        "Shadow Demon": "52.62%",
        "Lone Druid": "46.47%",
        "Juggernaut": "50.13%",
        "Oracle": "54.23%",
        "Elder Titan": "50.24%",
        "Tinker": "54.95%",
        "Bloodseeker": "47.83%",
        "Arc Warden": "52.83%",
        "Zeus": "47.94%",
        "Spectre": "48.13%",
        "Clockwerk": "48.93%",
        "Beastmaster": "49.64%"
    }
}